pyXLMS/__init__.py
pyXLMS/constants.py
pyXLMS/data.py
pyXLMS/pipelines.py
pyXLMS/exporter/__init__.py
pyXLMS/exporter/to_alphalink2.py
pyXLMS/exporter/to_impxfdr.py
pyXLMS/exporter/to_msannika.py
pyXLMS/exporter/to_proxl.py
pyXLMS/exporter/to_proxl_util.py
pyXLMS/exporter/to_pyxlinkviewer.py
pyXLMS/exporter/to_xifdr.py
pyXLMS/exporter/to_xinet.py
pyXLMS/exporter/to_xiview.py
pyXLMS/exporter/to_xlinkdb.py
pyXLMS/exporter/to_xlmstools.py
pyXLMS/exporter/to_xmas.py
pyXLMS/exporter/util.py
pyXLMS/parser/__init__.py
pyXLMS/parser/parser_xldbse_custom.py
pyXLMS/parser/parser_xldbse_maxquant.py
pyXLMS/parser/parser_xldbse_merox.py
pyXLMS/parser/parser_xldbse_msannika.py
pyXLMS/parser/parser_xldbse_mzid.py
pyXLMS/parser/parser_xldbse_plink.py
pyXLMS/parser/parser_xldbse_scout.py
pyXLMS/parser/parser_xldbse_xi.py
pyXLMS/parser/parser_xldbse_xlinkx.py
pyXLMS/parser/util.py
pyXLMS/plotting/__init__.py
pyXLMS/plotting/plot_crosslink_type_distribution.py
pyXLMS/plotting/plot_peptide_pair_distribution.py
pyXLMS/plotting/plot_protein_distribution.py
pyXLMS/plotting/plot_score_distribution.py
pyXLMS/plotting/plot_target_decoy_distribution.py
pyXLMS/plotting/plot_venn_diagram.py
pyXLMS/transform/__init__.py
pyXLMS/transform/aggregate.py
pyXLMS/transform/annotate_fdr.py
pyXLMS/transform/filter.py
pyXLMS/transform/from_dataframe.py
pyXLMS/transform/intersection.py
pyXLMS/transform/reannotate_positions.py
pyXLMS/transform/summary.py
pyXLMS/transform/targets_only.py
pyXLMS/transform/to_dataframe.py
pyXLMS/transform/to_proforma.py
pyXLMS/transform/util.py
pyXLMS/transform/validate.py
pyxlms-1.7.5.dist-info/licenses/LICENSE
pyxlms-1.7.5.dist-info/METADATA
pyxlms-1.7.5.dist-info/WHEEL
pyxlms-1.7.5.dist-info/top_level.txt
pyxlms-1.7.5.dist-info/RECORD
