Metadata-Version: 2.4
Name: pyXLMS
Version: 1.7.5
Summary: A python package to process protein cross-linking data.
Author-email: Micha Johannes Birklbauer <micha.birklbauer@fh-hagenberg.at>
Maintainer-email: Micha Johannes Birklbauer <micha.birklbauer@fh-hagenberg.at>
License: MIT License
Project-URL: Homepage, https://hgb-bin-proteomics.github.io/pyXLMS
Project-URL: Documentation, https://hgb-bin-proteomics.github.io/pyXLMS-docs
Project-URL: Repository, https://github.com/hgb-bin-proteomics/pyXLMS.git
Project-URL: Issues, https://github.com/hgb-bin-proteomics/pyXLMS/issues
Keywords: crosslink,crosslinker,crosslinking,mass spectrometry,proteomics
Classifier: Programming Language :: Python :: 3 :: Only
Classifier: License :: OSI Approved :: MIT License
Classifier: Operating System :: OS Independent
Classifier: Intended Audience :: Science/Research
Classifier: Topic :: Scientific/Engineering :: Bio-Informatics
Classifier: Development Status :: 5 - Production/Stable
Requires-Python: >=3.7
License-File: LICENSE
Requires-Dist: numpy
Requires-Dist: pandas
Requires-Dist: openpyxl
Requires-Dist: tqdm
Requires-Dist: pyteomics[XML]
Requires-Dist: biopython
Requires-Dist: biopandas
Requires-Dist: matplotlib
Requires-Dist: matplotlib-venn
Requires-Dist: pyarrow
Requires-Dist: lxml
Provides-Extra: gui
Requires-Dist: streamlit>=1.50.0; extra == "gui"
Requires-Dist: xlsxwriter; extra == "gui"
Requires-Dist: uv; extra == "gui"
Provides-Extra: docs
Requires-Dist: sphinx; extra == "docs"
Requires-Dist: pydata-sphinx-theme; extra == "docs"
Requires-Dist: myst-parser; extra == "docs"
Requires-Dist: sphinx-copybutton; extra == "docs"
Provides-Extra: dev
Requires-Dist: streamlit>=1.50.0; extra == "dev"
Requires-Dist: xlsxwriter; extra == "dev"
Requires-Dist: sphinx; extra == "dev"
Requires-Dist: pydata-sphinx-theme; extra == "dev"
Requires-Dist: myst-parser; extra == "dev"
Requires-Dist: sphinx-copybutton; extra == "dev"
Requires-Dist: uv; extra == "dev"
Requires-Dist: ruff; extra == "dev"
Requires-Dist: pyright; extra == "dev"
Requires-Dist: pytest; extra == "dev"
Dynamic: license-file
